RLUtilities/DetectCollisions.cp36-win_amd64.pyd
RLUtilities/DetectCollisions.cp37-win_amd64.pyd
RLUtilities/GameInfo.py
RLUtilities/Goal.py
RLUtilities/LinearAlgebra.cp36-win_amd64.pyd
RLUtilities/LinearAlgebra.cp37-win_amd64.pyd
RLUtilities/Maneuvers.py
RLUtilities/Mechanics.cp36-win_amd64.pyd
RLUtilities/Mechanics.cp37-win_amd64.pyd
RLUtilities/Simulation.cp36-win_amd64.pyd
RLUtilities/Simulation.cp37-win_amd64.pyd
RLUtilities/__init__.py
RLUtilities/controller_input.py
RLUtilities-0.0.13.dist-info/METADATA
RLUtilities-0.0.13.dist-info/WHEEL
RLUtilities-0.0.13.dist-info/top_level.txt
RLUtilities-0.0.13.dist-info/RECORD
