Metadata-Version: 2.1
Name: RLUtilities
Version: 0.0.13
Summary: tools for controlling Rocket League bots
Home-page: https://github.com/samuelpmish/RLUtilities
Author: Sam Mish
Author-email: samuelpmish@gmail.com
License: UNKNOWN
Platform: UNKNOWN
Classifier: Programming Language :: Python :: 3.6
Classifier: Programming Language :: Python :: 3.7
Classifier: Operating System :: Microsoft :: Windows
Requires-Python: >=3
